lzfse.cp312-win32.pyd
lzfse/src/lzfse.h
lzfse/src/lzfse_decode.c
lzfse/src/lzfse_decode_base.c
lzfse/src/lzfse_encode.c
lzfse/src/lzfse_encode_base.c
lzfse/src/lzfse_encode_tables.h
lzfse/src/lzfse_fse.c
lzfse/src/lzfse_fse.h
lzfse/src/lzfse_internal.h
lzfse/src/lzfse_main.c
lzfse/src/lzfse_tunables.h
lzfse/src/lzvn_decode_base.c
lzfse/src/lzvn_decode_base.h
lzfse/src/lzvn_encode_base.c
lzfse/src/lzvn_encode_base.h
lzfse-0.4.2.dist-info/AUTHORS
lzfse-0.4.2.dist-info/COPYING
lzfse-0.4.2.dist-info/LICENSE.lzfse
lzfse-0.4.2.dist-info/METADATA
lzfse-0.4.2.dist-info/WHEEL
lzfse-0.4.2.dist-info/top_level.txt
lzfse-0.4.2.dist-info/RECORD
