Metadata-Version: 2.1
Name: lzfse
Version: 0.4.2
Summary: Python bindings for the LZFSE reference implementation
Author-email: Yogesh Khatri <yogesh@swiftforensics.com>
Maintainer-email: m1sta <adamhamdi31@gmail.com>
License: MIT
Project-URL: Bug Tracker, https://github.com/m1stadev/lzfse/issues
Requires-Python: >=3.8
License-File: LICENSE.lzfse
License-File: COPYING
License-File: AUTHORS
